prithi_package-0.0.1.dist-info/METADATA
prithi_package-0.0.1.dist-info/RECORD
prithi_package-0.0.1.dist-info/WHEEL
prithi_package-0.0.1.dist-info/top_level.txt
sub1/__init__.py
sub2/__init__.py
