Metadata-Version: 2.1
Name: prithi-package
Version: 0.0.1
Summary: practice package
Home-page: https://github.com/PrithiPal
Author: prithi pal singh 
Author-email: prithipal.singh285@gmail.com
License: UNKNOWN
Platform: UNKNOWN
Classifier: Programming Language :: Python :: 3
Classifier: License :: OSI Approved :: MIT License
Classifier: Operating System :: OS Independent
